{
"event_detail":{
"properties":{
"user_ip":{
"type":"string",
"index":"not_analyzed"
},
"user_agent":{
"type":"string",
"index":"not_analyzed"
},
"gooru_uid":{
"type":"string",
"index":"not_analyzed"
},
"score":{
"type":"long",
"index":"not_analyzed"
},
"organization_uid":{
"type":"string",
"index":"not_analyzed"
},
"page_location":{
"type":"string",
"index":"not_analyzed"
},
"client_source":{
"type":"string",
"index":"not_analyzed"
},
"api_key":{
"type":"string",
"index":"not_analyzed"
},
"session_token":{
"type":"string",
"index":"not_analyzed"
},
"event_id":{
"type":"string",
"index":"not_analyzed"
},
"path":{
"type":"string",
"index":"not_analyzed"
},
"question_type":{
"type":"string",
"index":"not_analyzed"
},
"imei_code":{
"type":"string",
"index":"not_analyzed"
},
"attempt_count":{
"type":"long",
"index":"not_analyzed"
},
"item_type":{
"type":"string",
"index":"not_analyzed"
},
"resource_type":{
"type":"string",
"index":"not_analyzed"
},
"content_gooru_id":{
"type":"string",
"index":"not_analyzed"
},
"parent_gooru_id":{
"type":"string",
"index":"not_analyzed"
},
"session_id":{
"type":"string",
"index":"not_analyzed"
},
"parent_event_id":{
"type":"string",
"index":"not_analyzed"
},
"total_timespent_ms":{
"type":"long",
"index":"not_analyzed"
},
"context":{
"type":"string",
"index":"not_analyzed"
},
"event_name":{
"type":"string",
"index":"not_analyzed"
},
"rating":{
"type":"double",
"index":"not_analyzed"
},
"subject":{
"type":"String",
"index":"not_analyzed"
},
"course":{
"type":"String",
"index":"not_analyzed"
},
"unit":{
"type":"String",
"index":"not_analyzed"
},
"topic":{
"type":"String",
"index":"not_analyzed"
},
"lesson":{
"type":"String",
"index":"not_analyzed"
},
"concept":{
"type":"String",
"index":"not_analyzed"
},
"standards":{
"type":"string",
"index":"not_analyzed"
},
"state":{
"type":"Long",
"index":"not_analyzed"
},"district":{
"type":"Long",
"index":"not_analyzed"
},
"school":{
"type":"Long",
"index":"not_analyzed"
},
"class":{
"type":"String",
"index":"not_analyzed"
},
"teacher":{
"type":"String",
"index":"not_analyzed"
},
"title":{
"type":"string",
"index":"not_analyzed"
},"description":{
"type":"string",
"index":"not_analyzed"
},"sharing":{
"type":"string",
"index":"not_analyzed"
},
"content_type":{
"type":"string",
"index":"not_analyzed"
},"license":{
"type":"string",
"index":"not_analyzed"
},
"start_time":{
"format":"date_time",
"type":"date",
"index":"not_analyzed"
},
"event_time":{
"format":"date_time",
"type":"date",
"index":"not_analyzed"
},
"result_count":{
"type":"long",
"index":"not_analyzed"
},
"region":{
"type":"String",
"index":"not_analyzed"
},
"city":{
"type":"String",
"index":"not_analyzed"
},
"latitude":{
"type":"double"
},
"longitude":{
"type":"double"
}
}
}
}
